Workbook

Sheet Cover
B2: Cascade Components Corp.
B3: LBO Operating Model — Middle-Market Case Study
B4: Private Equity Course · Modules 4–5 · built one schedule at a time
B6: Cascade Components designs and manufactures engineered fastening and sealing components for aerospace, defense, and industrial OEMs. Founded 1994; family-owned; the founder-CEO is retiring and running a sale process. A classic middle-market LBO target: a stable niche business with real assets, recurring OEM relationships, and room for a buy-and-build roll-up.
B11: How to read this model
B12: ■ Blue text | C12: Hardcoded input / assumption — the levers you edit
B13: ■ Black text | C13: Formula / calculation — do not overwrite
B14: ■ Green text | C14: Link pulled from another sheet
B15: ■ Yellow fill | C15: Key assumption to set (also blue text)
B17: Units & conventions
B18: • All figures in $ millions unless noted; one decimal place.
B19: • Percentages are stored as fractions (0.181 renders 18.1%).
B20: • Valuation multiples shown as 0.0x. Years are text labels.
B21: • Illustrative case study — figures are realistic but not a real company.
B24: Tabs
B25: Cover | C25: This page — company, legend, conventions
B26: Assumptions | C26: All operating & transaction drivers (Module 4–5)
B27: EBITDA Bridge | C27: Reported → Adjusted EBITDA reconciliation (Module 3/4)
B28: Income Statement | C28: Historical + projected P&L → EBITDA/EBIT (Module 4)
B29: Balance Sheet | C29: Working capital (DSO/DIO/DPO) + PP&E roll-forward (Module 4)
B30: Sources & Uses | C30: How the deal is funded at close (Module 5)
B31: Debt Schedule | C31: Cash-flow sweep + debt roll-forward; interest → P&L (Module 5)
B32: Returns | C32: Exit value, MOIC / IRR, value bridge & sensitivities (Module 5)
B35: Course structure follows the Wharton Online & Wall Street Prep PE Certificate syllabus. Independent study aid generated by Claude (Anthropic); directed and reviewed by Simer Sawhney, Co-founder, Voatz Inc. Educational use only — not investment advice; illustrative figures. v1.0 · August 2026

Sheet Assumptions
A1: Cascade Components — Model Assumptions
A3: HISTORICAL FINANCIALS ($mm)
B4: FY2023 | C4: FY2024 | D4: FY2025 | H4: Notes / source
A5: Revenue | B5: 289 | C5: 303.5 | D5: 320 | H5: Company financials (illustrative)
A6: Cost of goods sold | B6: -189 | C6: -198.3 | D6: -208 | H6: ≈ 65% of revenue
A7: Gross profit | B7: =B5+B6 -> 100 | C7: =C5+C6 -> 105.2 | D7: =D5+D6 -> 112 | H7: Revenue − COGS (formula)
A8: Gross margin % | B8: =B7/B5 -> 0.34602076 | C8: =C7/C5 -> 0.34662273 | D8: =D7/D5 -> 0.35 | H8: Gross profit ÷ Revenue
A9: SG&A (excl. D&A) | B9: -49.5 | C9: -51 | D9: -54 | H9: operating overhead
A10: Adjusted EBITDA | B10: =B7+B9 -> 50.5 | C10: =C7+C9 -> 54.2 | D10: =D7+D9 -> 58 | H10: Gross profit + SG&A; reconciled on EBITDA Bridge tab
A11: EBITDA margin % | B11: =B10/B5 -> 0.17474048 | C11: =C10/C5 -> 0.1785832 | D11: =D10/D5 -> 0.18125 | H11: EBITDA ÷ Revenue
A12: Depreciation & amort. | B12: 9.5 | C12: 9.9 | D12: 10.4 | H12: ≈ 3.3% of revenue
A13: Capital expenditures | B13: 11.6 | C13: 12.1 | D13: 12.8 | H13: ≈ 4% of revenue
A14: Revenue growth % | C14: =C5/B5-1 -> 0.05017301 | D14: =D5/C5-1 -> 0.054365733
A16: OPERATING ASSUMPTIONS (projection drivers)
B17: Year 1 | C17: Year 2 | D17: Year 3 | E17: Year 4 | F17: Year 5 | H17: Basis
A18: Revenue growth % | B18: 0.055 | C18: 0.06 | D18: 0.06 | E18: 0.055 | F18: 0.05 | H18: organic; buy-and-build adds later
A19: Gross margin % | B19: 0.35 | C19: 0.352 | D19: 0.354 | E19: 0.355 | F19: 0.355 | H19: modest mix/scale improvement
A20: SG&A % of revenue | B20: 0.168 | C20: 0.166 | D20: 0.164 | E20: 0.163 | F20: 0.162 | H20: operating leverage as it scales
A21: PP&E depreciation rate | B21: 0.12 | C21: 0.12 | D21: 0.12 | E21: 0.12 | F21: 0.12 | H21: straight-line on net PP&E (~8-yr life)
A22: Capex % of revenue | B22: 0.04 | C22: 0.04 | D22: 0.039 | E22: 0.038 | F22: 0.038 | H22: maintenance + modest growth
A23: Tax rate | B23: 0.25 | C23: 0.25 | D23: 0.25 | E23: 0.25 | F23: 0.25 | H23: blended federal + state
A25: WORKING CAPITAL & PP&E ASSUMPTIONS
B26: Value | H26: Drives
A27: DSO — days sales outstanding | B27: 55 | H27: accounts receivable
A28: DIO — days inventory outstanding | B28: 85 | H28: inventory (manufacturer -> high)
A29: DPO — days payables outstanding | B29: 45 | H29: accounts payable
A30: Opening net PP&E, end-FY2025 ($mm) | B30: 85 | H30: PP&E roll-forward base
A32: TRANSACTION ASSUMPTIONS (entry structure)
A33: Entry EV / LTM EBITDA multiple | B33: 9 | H33: purchase-price multiple
A34: Net debt / EBITDA (leverage) | B34: 5 | H34: turns of new debt at close
A35: Blended cost of debt | B35: 0.085 | H35: ≈ SOFR 3.6% + ~490 bps blended
A36: Exit EV / EBITDA multiple | B36: 9 | H36: exit = entry (no multiple expansion assumed)
A37: Hold period (years) | B37: 5 | H37: years to exit
A38: Transaction fees (% of EV) | B38: 0.025 | H38: advisory / legal / diligence
A39: Financing fees (% of new debt) | B39: 0.02 | H39: arrangement / OID
A40: Management rollover ($mm) | B40: 12 | H40: mgmt equity rolled into newco

Sheet EBITDA Bridge
A1: Cascade Components — EBITDA Bridge ($mm)
A2: Reported → Adjusted EBITDA. Each add-back is tagged by where it sits on the P&L and how defensible it is (Module 3 spectrum).
A4: $mm | B4: FY2023 | C4: FY2024 | D4: FY2025 | E4: Where on P&L | F4: Defensibility
A5: Reported EBITDA | B5: 47.5 | C5: 51 | D5: 54
A6: Owner-comp normalization | B6: 1.8 | C6: 2 | D6: 2.5 | E6: SG&A | F6: High — clean, quantifiable
A7: Facility relocation (one-time) | B7: 0 | C7: 0 | D7: 1.2 | E7: COGS + SG&A | F7: Medium — verify truly one-time
A8: Transaction & legal (non-recur.) | B8: 0.8 | C8: 0.7 | D8: 0.3 | E8: SG&A | F8: Medium — confirm non-operating
A9: Inventory write-down (non-recur.) | B9: 0.4 | C9: 0.5 | D9: 0 | E9: COGS | F9: Medium — check whether it recurs
A10: Total add-backs | B10: =SUM(B6:B9) -> 3 | C10: =SUM(C6:C9) -> 3.2 | D10: =SUM(D6:D9) -> 4
A11: Adjusted EBITDA | B11: =B5+B10 -> 50.5 | C11: =C5+C10 -> 54.2 | D11: =D5+D10 -> 58
A12: Adjusted EBITDA margin % | B12: =B11/Assumptions!B5 -> 0.17474048 | C12: =C11/Assumptions!C5 -> 0.1785832 | D12: =D11/Assumptions!D5 -> 0.18125
A13: Uplift over reported % | B13: =B11/B5-1 -> 0.063157895 | C13: =C11/C5-1 -> 0.062745098 | D13: =D11/D5-1 -> 0.074074074
A15: Check: Adjusted EBITDA − operating model | B15: =B11-Assumptions!B10 -> 0 | C15: =C11-Assumptions!C10 -> 0 | D15: =D11-Assumptions!D10 -> 0 | E15: zero confirms the tie ✓
A17: Defensibility (Module 3): High add-backs survive diligence; Medium ones need support; serial ‘one-offs’ and run-rate/pro-forma items are where buyers push back hardest.

Sheet Income Statement
A1: Cascade Components — Income Statement ($mm)
B3: Actual | E3: Projected
A4: $mm | B4: FY2023 | C4: FY2024 | D4: FY2025 | E4: Year 1 | F4: Year 2 | G4: Year 3 | H4: Year 4 | I4: Year 5
A5: Revenue | B5: =Assumptions!B5 -> 289 | C5: =Assumptions!C5 -> 303.5 | D5: =Assumptions!D5 -> 320 | E5: =D5*(1+Assumptions!B18) -> 337.6 | F5: =E5*(1+Assumptions!C18) -> 357.856 | G5: =F5*(1+Assumptions!D18) -> 379.32736 | H5: =G5*(1+Assumptions!E18) -> 400.19036 | I5: =H5*(1+Assumptions!F18) -> 420.19988
A6: growth % | C6: =C5/B5-1 -> 0.05017301 | D6: =D5/C5-1 -> 0.054365733 | E6: =E5/D5-1 -> 0.055 | F6: =F5/E5-1 -> 0.06 | G6: =G5/F5-1 -> 0.06 | H6: =H5/G5-1 -> 0.055 | I6: =I5/H5-1 -> 0.05
A7: Cost of goods sold | B7: =Assumptions!B6 -> -189 | C7: =Assumptions!C6 -> -198.3 | D7: =Assumptions!D6 -> -208 | E7: =-(E5*(1-Assumptions!B19)) -> -219.44 | F7: =-(F5*(1-Assumptions!C19)) -> -231.89069 | G7: =-(G5*(1-Assumptions!D19)) -> -245.04547 | H7: =-(H5*(1-Assumptions!E19)) -> -258.12279 | I7: =-(I5*(1-Assumptions!F19)) -> -271.02892
A8: Gross profit | B8: =B5+B7 -> 100 | C8: =C5+C7 -> 105.2 | D8: =D5+D7 -> 112 | E8: =E5+E7 -> 118.16 | F8: =F5+F7 -> 125.96531 | G8: =G5+G7 -> 134.28189 | H8: =H5+H7 -> 142.06758 | I8: =I5+I7 -> 149.17096
A9: gross margin % | B9: =B8/B5 -> 0.34602076 | C9: =C8/C5 -> 0.34662273 | D9: =D8/D5 -> 0.35 | E9: =E8/E5 -> 0.35 | F9: =F8/F5 -> 0.352 | G9: =G8/G5 -> 0.354 | H9: =H8/H5 -> 0.355 | I9: =I8/I5 -> 0.355
A10: SG&A (excl. D&A) | B10: =Assumptions!B9 -> -49.5 | C10: =Assumptions!C9 -> -51 | D10: =Assumptions!D9 -> -54 | E10: =-(E5*Assumptions!B20) -> -56.7168 | F10: =-(F5*Assumptions!C20) -> -59.404096 | G10: =-(G5*Assumptions!D20) -> -62.209687 | H10: =-(H5*Assumptions!E20) -> -65.231029 | I10: =-(I5*Assumptions!F20) -> -68.072381
A11: EBITDA | B11: =B8+B10 -> 50.5 | C11: =C8+C10 -> 54.2 | D11: =D8+D10 -> 58 | E11: =E8+E10 -> 61.4432 | F11: =F8+F10 -> 66.561216 | G11: =G8+G10 -> 72.072198 | H11: =H8+H10 -> 76.83655 | I11: =I8+I10 -> 81.098577
A12: EBITDA margin % | B12: =B11/B5 -> 0.17474048 | C12: =C11/C5 -> 0.1785832 | D12: =D11/D5 -> 0.18125 | E12: =E11/E5 -> 0.182 | F12: =F11/F5 -> 0.186 | G12: =G11/G5 -> 0.19 | H12: =H11/H5 -> 0.192 | I12: =I11/I5 -> 0.193
A13: Depreciation & amort. | B13: =-Assumptions!B12 -> -9.5 | C13: =-Assumptions!C12 -> -9.9 | D13: =-Assumptions!D12 -> -10.4 | E13: =-'Balance Sheet'!C15 -> -10.2 | F13: =-'Balance Sheet'!D15 -> -10.59648 | G13: =-'Balance Sheet'!E15 -> -11.042611 | H13: =-'Balance Sheet'!F15 -> -11.49275 | I13: =-'Balance Sheet'!G15 -> -11.938488
A14: EBIT | B14: =B11+B13 -> 41 | C14: =C11+C13 -> 44.3 | D14: =D11+D13 -> 47.6 | E14: =E11+E13 -> 51.2432 | F14: =F11+F13 -> 55.964736 | G14: =G11+G13 -> 61.029587 | H14: =H11+H13 -> 65.3438 | I14: =I11+I13 -> 69.160089
A15: EBIT margin % | B15: =B14/B5 -> 0.14186851 | C15: =C14/C5 -> 0.14596376 | D15: =D14/D5 -> 0.14875 | E15: =E14/E5 -> 0.15178673 | F15: =F14/F5 -> 0.15638898 | G15: =G14/G5 -> 0.16088897 | H15: =H14/H5 -> 0.16328179 | I15: =I14/I5 -> 0.16458855
A16: Interest expense | E16: =-'Debt Schedule'!C14 -> -24.65 | F16: =-'Debt Schedule'!D14 -> -23.567513 | G16: =-'Debt Schedule'!E14 -> -22.193621 | H16: =-'Debt Schedule'!F14 -> -20.434224 | I16: =-'Debt Schedule'!G14 -> -18.276004
A17: Pre-tax income | E17: =E14+E16 -> 26.5932 | F17: =F14+F16 -> 32.397223 | G17: =G14+G16 -> 38.835966 | H17: =H14+H16 -> 44.909576 | I17: =I14+I16 -> 50.884085
A18: Taxes | E18: =-MAX(E17,0)*Assumptions!B23 -> -6.6483 | F18: =-MAX(F17,0)*Assumptions!C23 -> -8.0993059 | G18: =-MAX(G17,0)*Assumptions!D23 -> -9.7089914 | H18: =-MAX(H17,0)*Assumptions!E23 -> -11.227394 | I18: =-MAX(I17,0)*Assumptions!F23 -> -12.721021
A19: Net income | E19: =E17+E18 -> 19.9449 | F19: =F17+F18 -> 24.297918 | G19: =G17+G18 -> 29.126974 | H19: =H17+H18 -> 33.682182 | I19: =I17+I18 -> 38.163064
A20: net margin % | E20: =E19/E5 -> 0.059078495 | F20: =F19/F5 -> 0.067898589 | G20: =G19/G5 -> 0.076785851 | H20: =H19/H5 -> 0.084165399 | I20: =I19/I5 -> 0.090821215
A22: Interest, taxes & net income (projected years) come from the Debt Schedule; historical periods pre-date the LBO capital structure.
A23: Convention: interest is charged on the beginning-of-year debt balance — the standard way to avoid a circular reference.

Sheet Balance Sheet
A1: Cascade Components — Balance Sheet & Working Capital ($mm)
A2: Operating (asset-side) balance sheet. Cash, debt, goodwill & equity are completed in Module 5 with the LBO financing.
A4: WORKING CAPITAL SCHEDULE (driven by DSO / DIO / DPO)
A5: $mm | B5: FY2025 | C5: Year 1 | D5: Year 2 | E5: Year 3 | F5: Year 4 | G5: Year 5
A6: Accounts receivable (DSO) | B6: =Assumptions!$B$27/365*'Income Statement'!D5 -> 48.219178 | C6: =Assumptions!$B$27/365*'Income Statement'!E5 -> 50.871233 | D6: =Assumptions!$B$27/365*'Income Statement'!F5 -> 53.923507 | E6: =Assumptions!$B$27/365*'Income Statement'!G5 -> 57.158917 | F6: =Assumptions!$B$27/365*'Income Statement'!H5 -> 60.302658 | G6: =Assumptions!$B$27/365*'Income Statement'!I5 -> 63.317791
A7: Inventory (DIO) | B7: =Assumptions!$B$28/365*(-'Income Statement'!D7) -> 48.438356 | C7: =Assumptions!$B$28/365*(-'Income Statement'!E7) -> 51.102466 | D7: =Assumptions!$B$28/365*(-'Income Statement'!F7) -> 54.001941 | E7: =Assumptions!$B$28/365*(-'Income Statement'!G7) -> 57.065384 | F7: =Assumptions!$B$28/365*(-'Income Statement'!H7) -> 60.110786 | G7: =Assumptions!$B$28/365*(-'Income Statement'!I7) -> 63.116325
A8: Accounts payable (DPO) | B8: =Assumptions!$B$29/365*(-'Income Statement'!D7) -> 25.643836 | C8: =Assumptions!$B$29/365*(-'Income Statement'!E7) -> 27.054247 | D8: =Assumptions!$B$29/365*(-'Income Statement'!F7) -> 28.589263 | E8: =Assumptions!$B$29/365*(-'Income Statement'!G7) -> 30.211086 | F8: =Assumptions!$B$29/365*(-'Income Statement'!H7) -> 31.823357 | G8: =Assumptions!$B$29/365*(-'Income Statement'!I7) -> 33.414525
A9: Net working capital | B9: =B6+B7-B8 -> 71.013699 | C9: =C6+C7-C8 -> 74.919452 | D9: =D6+D7-D8 -> 79.336185 | E9: =E6+E7-E8 -> 84.013216 | F9: =F6+F7-F8 -> 88.590086 | G9: =G6+G7-G8 -> 93.019591
A10: (Increase)/decrease in NWC — cash | C10: =-(C9-B9) -> -3.9057534 | D10: =-(D9-C9) -> -4.4167329 | E10: =-(E9-D9) -> -4.6770309 | F10: =-(F9-E9) -> -4.5768704 | G10: =-(G9-F9) -> -4.4295043
A12: PP&E ROLL-FORWARD (D&A now comes from the asset base)
A13: Beginning net PP&E | C13: =Assumptions!$B$30 -> 85 | D13: =C16 -> 88.304 | E13: =D16 -> 92.02176 | F13: =E16 -> 95.772916 | G13: =F16 -> 99.4874
A14: + Capital expenditures | C14: =Assumptions!B22*'Income Statement'!E5 -> 13.504 | D14: =Assumptions!C22*'Income Statement'!F5 -> 14.31424 | E14: =Assumptions!D22*'Income Statement'!G5 -> 14.793767 | F14: =Assumptions!E22*'Income Statement'!H5 -> 15.207234 | G14: =Assumptions!F22*'Income Statement'!I5 -> 15.967596
A15: − Depreciation | C15: =Assumptions!B21*C13 -> 10.2 | D15: =Assumptions!C21*D13 -> 10.59648 | E15: =Assumptions!D21*E13 -> 11.042611 | F15: =Assumptions!E21*F13 -> 11.49275 | G15: =Assumptions!F21*G13 -> 11.938488
A16: Ending net PP&E | B16: =Assumptions!$B$30 -> 85 | C16: =C13+C14-C15 -> 88.304 | D16: =D13+D14-D15 -> 92.02176 | E16: =E13+E14-E15 -> 95.772916 | F16: =F13+F14-F15 -> 99.4874 | G16: =G13+G14-G15 -> 103.51651
A18: OPERATING NET ASSETS (invested capital, excl. cash / debt / goodwill)
A19: Net working capital | B19: =B9 -> 71.013699 | C19: =C9 -> 74.919452 | D19: =D9 -> 79.336185 | E19: =E9 -> 84.013216 | F19: =F9 -> 88.590086 | G19: =G9 -> 93.019591
A20: Net PP&E | B20: =B16 -> 85 | C20: =C16 -> 88.304 | D20: =D16 -> 92.02176 | E20: =E16 -> 95.772916 | F20: =F16 -> 99.4874 | G20: =G16 -> 103.51651
A21: Operating net assets | B21: =B19+B20 -> 156.0137 | C21: =C19+C20 -> 163.22345 | D21: =D19+D20 -> 171.35794 | E21: =E19+E20 -> 179.78613 | F21: =F19+F20 -> 188.07749 | G21: =G19+G20 -> 196.5361
A23: Growth eats cash: NWC rises every year, so the "(Increase)/decrease in NWC" line is a recurring cash outflow (row 10).
A24: D&A fix: Income-Statement depreciation now links to row 15 (rate × beginning PP&E) — no longer a % of revenue.

Sheet Sources & Uses
A1: Cascade Components — Sources & Uses ($mm)
A2: How the purchase is funded at close. Uses = what you pay for; Sources = where the money comes from. They must balance.
A4: ENTRY
A5: LTM Adjusted EBITDA | B5: =Assumptions!$D$10 -> 58 | C5: from EBITDA Bridge (FY2025)
A6: Entry EV / EBITDA multiple | B6: =Assumptions!$B$33 -> 9 | C6: purchase-price multiple
A7: Entry enterprise value | B7: =B6*B5 -> 522 | C7: multiple × EBITDA
A9: USES OF FUNDS
A10: Purchase enterprise value | B10: =B7 -> 522 | C10: buy the business (cash-free, debt-free)
A11: Transaction fees | B11: =Assumptions!$B$38*B7 -> 13.05 | C11: advisory / legal / diligence
A12: Financing fees | B12: =Assumptions!$B$39*(Assumptions!$B$34*Assumptions!$D$10) -> 5.8 | C12: arrangement / OID on new debt
A13: Total uses | B13: =SUM(B10:B12) -> 540.85
A15: SOURCES OF FUNDS
A16: New term debt | B16: =Assumptions!$B$34*Assumptions!$D$10 -> 290 | C16: leverage × EBITDA (5.0×)
A17: Management rollover | B17: =Assumptions!$B$40 -> 12 | C17: mgmt equity rolled into newco
A18: Sponsor equity (plug) | B18: =B13-B16-B17 -> 238.85 | C18: the check the PE firm writes
A19: Total sources | B19: =SUM(B16:B18) -> 540.85
A21: Check: sources − uses | B21: =B19-B13 -> 0 | C21: 0 confirms it balances ✓
A23: CAPITALIZATION
A24: Total capitalization | B24: =B13 -> 540.85
A25: Debt % of total | B25: =B16/B13 -> 0.53619303
A26: Equity % of total | B26: =(B17+B18)/B13 -> 0.46380697
A27: Sponsor equity check | B27: =B18 -> 238.85 | C27: business equity 232.0 + fees − rollover
A29: Reconciles to Returns: sponsor check 238.9 = business equity 232.0 (EV − debt) + fees 18.9 − rollover 12.0.

Sheet Debt Schedule
A1: Cascade Components — Debt Schedule ($mm)
A2: Free cash flow sweeps the debt down each year; interest (on the beginning balance) feeds the income statement.
A4: $mm | B4: At close | C4: Year 1 | D4: Year 2 | E4: Year 3 | F4: Year 4 | G4: Year 5
A5: CASH FLOW AVAILABLE FOR DEBT PAYDOWN
A6: Net income | C6: ='Income Statement'!E19 -> 19.9449 | D6: ='Income Statement'!F19 -> 24.297918 | E6: ='Income Statement'!G19 -> 29.126974 | F6: ='Income Statement'!H19 -> 33.682182 | G6: ='Income Statement'!I19 -> 38.163064
A7: + Depreciation & amort. | C7: ='Balance Sheet'!C15 -> 10.2 | D7: ='Balance Sheet'!D15 -> 10.59648 | E7: ='Balance Sheet'!E15 -> 11.042611 | F7: ='Balance Sheet'!F15 -> 11.49275 | G7: ='Balance Sheet'!G15 -> 11.938488
A8: − (Increase)/decrease in NWC | C8: ='Balance Sheet'!C10 -> -3.9057534 | D8: ='Balance Sheet'!D10 -> -4.4167329 | E8: ='Balance Sheet'!E10 -> -4.6770309 | F8: ='Balance Sheet'!F10 -> -4.5768704 | G8: ='Balance Sheet'!G10 -> -4.4295043
A9: − Capital expenditures | C9: =-'Balance Sheet'!C14 -> -13.504 | D9: =-'Balance Sheet'!D14 -> -14.31424 | E9: =-'Balance Sheet'!E14 -> -14.793767 | F9: =-'Balance Sheet'!F14 -> -15.207234 | G9: =-'Balance Sheet'!G14 -> -15.967596
A10: Free cash flow (pre-paydown) | C10: =SUM(C6:C9) -> 12.735147 | D10: =SUM(D6:D9) -> 16.163425 | E10: =SUM(E6:E9) -> 20.698788 | F10: =SUM(F6:F9) -> 25.390827 | G10: =SUM(G6:G9) -> 29.704452
A12: DEBT ROLL-FORWARD
A13: Beginning debt | C13: =B16 -> 290 | D13: =C16 -> 277.26485 | E13: =D16 -> 261.10143 | F13: =E16 -> 240.40264 | G13: =F16 -> 215.01181
A14: Interest expense (@ 8.5%) | C14: =C13*Assumptions!$B$35 -> 24.65 | D14: =D13*Assumptions!$B$35 -> 23.567513 | E14: =E13*Assumptions!$B$35 -> 22.193621 | F14: =F13*Assumptions!$B$35 -> 20.434224 | G14: =G13*Assumptions!$B$35 -> 18.276004
A15: (−) Debt paydown — cash sweep | C15: =-MIN(MAX(C10,0),C13) -> -12.735147 | D15: =-MIN(MAX(D10,0),D13) -> -16.163425 | E15: =-MIN(MAX(E10,0),E13) -> -20.698788 | F15: =-MIN(MAX(F10,0),F13) -> -25.390827 | G15: =-MIN(MAX(G10,0),G13) -> -29.704452
A16: Ending debt | B16: ='Sources & Uses'!B16 -> 290 | C16: =C13+C15 -> 277.26485 | D16: =D13+D15 -> 261.10143 | E16: =E13+E15 -> 240.40264 | F16: =F13+F15 -> 215.01181 | G16: =G13+G15 -> 185.30736
A17: Memo: net debt / EBITDA | C17: =C16/'Income Statement'!E11 -> 4.5125393 | D17: =D16/'Income Statement'!F11 -> 3.9227262 | E17: =E16/'Income Statement'!G11 -> 3.3355808 | F17: =F16/'Income Statement'!H11 -> 2.7983012 | G17: =G16/'Income Statement'!I11 -> 2.2849644
A19: 100% cash sweep assumed (all free cash flow pays down debt). Interest is charged on the beginning-of-year balance to keep the model non-circular.

Sheet Returns
A1: Cascade Components — Returns ($mm)
A2: Exit equity ÷ equity invested = MOIC; annualized = IRR. The bridge attributes the gain to the three value levers (1.6).
A4: ENTRY
A5: Entry enterprise value | B5: ='Sources & Uses'!B7 -> 522
A6: Less: new debt | B6: =-'Sources & Uses'!B16 -> -290
A7: Entry equity (business) | B7: =B5+B6 -> 232 | C7: EV − debt (not the sponsor check: that adds fees, nets rollover)
A8: Plus: fees funded by equity | B8: ='Sources & Uses'!B11+'Sources & Uses'!B12 -> 18.85 | C8: transaction + financing
A9: Total equity invested | B9: =B7+B8 -> 250.85 | C9: sponsor + rollover
A11: EXIT (Year 5)
A12: Year-5 EBITDA | B12: ='Income Statement'!I11 -> 81.098577
A13: Exit EV / EBITDA multiple | B13: =Assumptions!B36 -> 9 | C13: exit = entry (no expansion)
A14: Exit enterprise value | B14: =B12*B13 -> 729.8872
A15: Less: exit net debt | B15: =-'Debt Schedule'!G16 -> -185.30736 | C15: after 5 yrs of paydown
A16: Exit equity | B16: =B14+B15 -> 544.57984
A18: RETURNS
A19: MOIC | B19: =B16/B9 -> 2.1709382 | C19: exit equity ÷ TOTAL equity invested (B16 ÷ B9 = 544.6 ÷ 250.8)
A20: IRR (5-yr) | B20: =B19^(1/Assumptions!B37)-1 -> 0.16769519 | C20: MOIC annualized over the hold
A22: VALUE-CREATION BRIDGE (the three levers, 1.6)
A24: Entry equity (business, EV − debt) | B24: =B7 -> 232 | D24: % of gain
A25: + EBITDA growth | B25: =('Income Statement'!I11-Assumptions!D10)*Assumptions!B33 -> 207.8872 | C25: ΔEBITDA × entry multiple | D25: =B25/(B28-B24) -> 0.66506912
A26: + Multiple expansion | B26: =(Assumptions!B36-Assumptions!B33)*'Income Statement'!I11 -> 0 | C26: Δmultiple × exit EBITDA | D26: =B26/(B28-B24) -> 0
A27: + Debt paydown (deleveraging) | B27: ='Sources & Uses'!B16-'Debt Schedule'!G16 -> 104.69264 | C27: debt repaid over the hold | D27: =B27/(B28-B24) -> 0.33493088
A28: Exit equity (sum of bridge) | B28: =SUM(B24:B27) -> 544.57984
A29: check vs exit equity | B29: =B28-B16 -> 0 | C29: 0 confirms the bridge ties
A31: SENSITIVITY — MOIC (entry multiple ↓ × exit multiple →)
A32: entry \ exit | B32: 8 | C32: 8.5 | D32: 9 | E32: 9.5 | F32: 10
A33: 8 | B33: =('Income Statement'!I11*B$32-'Debt Schedule'!G16)/($A33*Assumptions!D10*(1+Assumptions!$B$38)+Assumptions!$B$39*'Sources & Uses'!B16-'Sources & Uses'!B16) -> 2.4215322 | C33: =('Income Statement'!I11*C$32-'Debt Schedule'!G16)/($A33*Assumptions!D10*(1+Assumptions!$B$38)+Assumptions!$B$39*'Sources & Uses'!B16-'Sources & Uses'!B16) -> 2.6333884 | D33: =('Income Statement'!I11*D$32-'Debt Schedule'!G16)/($A33*Assumptions!D10*(1+Assumptions!$B$38)+Assumptions!$B$39*'Sources & Uses'!B16-'Sources & Uses'!B16) -> 2.8452447 | E33: =('Income Statement'!I11*E$32-'Debt Schedule'!G16)/($A33*Assumptions!D10*(1+Assumptions!$B$38)+Assumptions!$B$39*'Sources & Uses'!B16-'Sources & Uses'!B16) -> 3.057101 | F33: =('Income Statement'!I11*F$32-'Debt Schedule'!G16)/($A33*Assumptions!D10*(1+Assumptions!$B$38)+Assumptions!$B$39*'Sources & Uses'!B16-'Sources & Uses'!B16) -> 3.2689572
A34: 8.5 | B34: =('Income Statement'!I11*B$32-'Debt Schedule'!G16)/($A34*Assumptions!D10*(1+Assumptions!$B$38)+Assumptions!$B$39*'Sources & Uses'!B16-'Sources & Uses'!B16) -> 2.0960147 | C34: =('Income Statement'!I11*C$32-'Debt Schedule'!G16)/($A34*Assumptions!D10*(1+Assumptions!$B$38)+Assumptions!$B$39*'Sources & Uses'!B16-'Sources & Uses'!B16) -> 2.279392 | D34: =('Income Statement'!I11*D$32-'Debt Schedule'!G16)/($A34*Assumptions!D10*(1+Assumptions!$B$38)+Assumptions!$B$39*'Sources & Uses'!B16-'Sources & Uses'!B16) -> 2.4627692 | E34: =('Income Statement'!I11*E$32-'Debt Schedule'!G16)/($A34*Assumptions!D10*(1+Assumptions!$B$38)+Assumptions!$B$39*'Sources & Uses'!B16-'Sources & Uses'!B16) -> 2.6461464 | F34: =('Income Statement'!I11*F$32-'Debt Schedule'!G16)/($A34*Assumptions!D10*(1+Assumptions!$B$38)+Assumptions!$B$39*'Sources & Uses'!B16-'Sources & Uses'!B16) -> 2.8295236
A35: 9 | B35: =('Income Statement'!I11*B$32-'Debt Schedule'!G16)/($A35*Assumptions!D10*(1+Assumptions!$B$38)+Assumptions!$B$39*'Sources & Uses'!B16-'Sources & Uses'!B16) -> 1.847643 | C35: =('Income Statement'!I11*C$32-'Debt Schedule'!G16)/($A35*Assumptions!D10*(1+Assumptions!$B$38)+Assumptions!$B$39*'Sources & Uses'!B16-'Sources & Uses'!B16) -> 2.0092906 | D35: =('Income Statement'!I11*D$32-'Debt Schedule'!G16)/($A35*Assumptions!D10*(1+Assumptions!$B$38)+Assumptions!$B$39*'Sources & Uses'!B16-'Sources & Uses'!B16) -> 2.1709382 | E35: =('Income Statement'!I11*E$32-'Debt Schedule'!G16)/($A35*Assumptions!D10*(1+Assumptions!$B$38)+Assumptions!$B$39*'Sources & Uses'!B16-'Sources & Uses'!B16) -> 2.3325857 | F35: =('Income Statement'!I11*F$32-'Debt Schedule'!G16)/($A35*Assumptions!D10*(1+Assumptions!$B$38)+Assumptions!$B$39*'Sources & Uses'!B16-'Sources & Uses'!B16) -> 2.4942333
A36: 9.5 | B36: =('Income Statement'!I11*B$32-'Debt Schedule'!G16)/($A36*Assumptions!D10*(1+Assumptions!$B$38)+Assumptions!$B$39*'Sources & Uses'!B16-'Sources & Uses'!B16) -> 1.6518979 | C36: =('Income Statement'!I11*C$32-'Debt Schedule'!G16)/($A36*Assumptions!D10*(1+Assumptions!$B$38)+Assumptions!$B$39*'Sources & Uses'!B16-'Sources & Uses'!B16) -> 1.79642 | D36: =('Income Statement'!I11*D$32-'Debt Schedule'!G16)/($A36*Assumptions!D10*(1+Assumptions!$B$38)+Assumptions!$B$39*'Sources & Uses'!B16-'Sources & Uses'!B16) -> 1.9409421 | E36: =('Income Statement'!I11*E$32-'Debt Schedule'!G16)/($A36*Assumptions!D10*(1+Assumptions!$B$38)+Assumptions!$B$39*'Sources & Uses'!B16-'Sources & Uses'!B16) -> 2.0854642 | F36: =('Income Statement'!I11*F$32-'Debt Schedule'!G16)/($A36*Assumptions!D10*(1+Assumptions!$B$38)+Assumptions!$B$39*'Sources & Uses'!B16-'Sources & Uses'!B16) -> 2.2299863
A37: 10 | B37: =('Income Statement'!I11*B$32-'Debt Schedule'!G16)/($A37*Assumptions!D10*(1+Assumptions!$B$38)+Assumptions!$B$39*'Sources & Uses'!B16-'Sources & Uses'!B16) -> 1.4936554 | C37: =('Income Statement'!I11*C$32-'Debt Schedule'!G16)/($A37*Assumptions!D10*(1+Assumptions!$B$38)+Assumptions!$B$39*'Sources & Uses'!B16-'Sources & Uses'!B16) -> 1.6243331 | D37: =('Income Statement'!I11*D$32-'Debt Schedule'!G16)/($A37*Assumptions!D10*(1+Assumptions!$B$38)+Assumptions!$B$39*'Sources & Uses'!B16-'Sources & Uses'!B16) -> 1.7550107 | E37: =('Income Statement'!I11*E$32-'Debt Schedule'!G16)/($A37*Assumptions!D10*(1+Assumptions!$B$38)+Assumptions!$B$39*'Sources & Uses'!B16-'Sources & Uses'!B16) -> 1.8856884 | F37: =('Income Statement'!I11*F$32-'Debt Schedule'!G16)/($A37*Assumptions!D10*(1+Assumptions!$B$38)+Assumptions!$B$39*'Sources & Uses'!B16-'Sources & Uses'!B16) -> 2.0163661
A40: SENSITIVITY — IRR (entry multiple ↓ × exit multiple →)
A41: entry \ exit | B41: 8 | C41: 8.5 | D41: 9 | E41: 9.5 | F41: 10
A42: 8 | B42: =B33^(1/Assumptions!B37)-1 -> 0.19348798 | C42: =C33^(1/Assumptions!B37)-1 -> 0.21367662 | D42: =D33^(1/Assumptions!B37)-1 -> 0.232605 | E42: =E33^(1/Assumptions!B37)-1 -> 0.2504374 | F42: =F33^(1/Assumptions!B37)-1 -> 0.26730704
A43: 8.5 | B43: =B34^(1/Assumptions!B37)-1 -> 0.15952166 | C43: =C34^(1/Assumptions!B37)-1 -> 0.17913574 | D43: =D34^(1/Assumptions!B37)-1 -> 0.19752542 | E43: =E34^(1/Assumptions!B37)-1 -> 0.21485032 | F43: =F34^(1/Assumptions!B37)-1 -> 0.23123985
A44: 9 | B44: =B35^(1/Assumptions!B37)-1 -> 0.1306381 | C44: =C35^(1/Assumptions!B37)-1 -> 0.14976359 | D44: =D35^(1/Assumptions!B37)-1 -> 0.16769519 | E44: =E35^(1/Assumptions!B37)-1 -> 0.18458853 | F44: =F35^(1/Assumptions!B37)-1 -> 0.2005698
A45: 9.5 | B45: =B36^(1/Assumptions!B37)-1 -> 0.10559646 | C45: =C36^(1/Assumptions!B37)-1 -> 0.12429836 | D45: =D36^(1/Assumptions!B37)-1 -> 0.14183281 | E45: =E36^(1/Assumptions!B37)-1 -> 0.15835199 | F45: =F36^(1/Assumptions!B37)-1 -> 0.1739793
A46: 10 | B46: =B37^(1/Assumptions!B37)-1 -> 0.083552804 | C46: =C37^(1/Assumptions!B37)-1 -> 0.10188182 | D46: =D37^(1/Assumptions!B37)-1 -> 0.11906666 | E46: =E37^(1/Assumptions!B37)-1 -> 0.13525648 | F46: =F37^(1/Assumptions!B37)-1 -> 0.15057221
A48: Base case (entry 9.0× / exit 9.0×) highlighted. MOIC = exit equity ÷ total equity invested ($250.8M — sponsor + rollover, incl. fees), the same denominator as the headline. Exit debt is held constant across the grid — the paydown path depends on operations, not the purchase multiple.
